README.md
setup.cfg
setup.py
entropy/__init__.py
entropy/date_utils.py
entropy/entropy.py
entropy/file_utils.py
entropy/journal.py
entropy/status.py
entropy/time_to_object.py
entropy.egg-info/PKG-INFO
entropy.egg-info/SOURCES.txt
entropy.egg-info/dependency_links.txt
entropy.egg-info/entry_points.txt
entropy.egg-info/requires.txt
entropy.egg-info/top_level.txt