Metadata-Version: 1.0
Name: entropy
Version: 0.1.0
Summary: entropy is a command line friend that helps you reduce entropy in your life
Home-page: https://github.com/h4ck3rk3y/entropy
Author: Gyanendra Mishra
Author-email: anomaly.the@gmail.com
License: MIT
Keywords: entropy,productivity,journaling
Platform: UNKNOWN
